poetry_stale_dependencies/__init__.py
poetry_stale_dependencies/_version.py
poetry_stale_dependencies/config.py
poetry_stale_dependencies/inspections.py
poetry_stale_dependencies/lock_spec.py
poetry_stale_dependencies/plugin.py
poetry_stale_dependencies/project_spec.py
poetry_stale_dependencies/remote.py
poetry_stale_dependencies/util.py
poetry_stale_dependencies-0.2.2.dist-info/LICENSE
poetry_stale_dependencies-0.2.2.dist-info/METADATA
poetry_stale_dependencies-0.2.2.dist-info/WHEEL
poetry_stale_dependencies-0.2.2.dist-info/entry_points.txt
poetry_stale_dependencies-0.2.2.dist-info/RECORD
