Metadata-Version: 2.1
Name: poetry-stale-dependencies
Version: 0.2.2
Summary: 
Author: Biocatch LTD
Author-email: you@example.com
Requires-Python: >=3.10,<4.0
Classifier: Programming Language :: Python :: 3
Classifier: Programming Language :: Python :: 3.10
Classifier: Programming Language :: Python :: 3.11
Classifier: Programming Language :: Python :: 3.12
Requires-Dist: cleo (>=2.1.0,<3.0.0)
Requires-Dist: httpx (>=0.27.0,<0.28.0)
Requires-Dist: poetry (>=1.7.1,<2.0.0)
Requires-Dist: tomli (>=2.0.1,<3.0.0)
